README.rst
setup.py
ttd.py
ttd.egg-info/PKG-INFO
ttd.egg-info/SOURCES.txt
ttd.egg-info/dependency_links.txt
ttd.egg-info/not-zip-safe
ttd.egg-info/top_level.txt