Metadata-Version: 1.1
Name: ttd
Version: 0.1.0
Summary: Time Till Done (ttd) is a simple progress bar for your long running Python scripts
Home-page: https://github.com/JarrodCTaylor/ttd
Author: Jarrod C Taylor
Author-email: jarrod.c.taylor@gmail.com
License: WTFPL
Platform: UNKNOWN
Classifier: Environment :: Console
Classifier: Topic :: Terminals
Classifier: Topic :: System :: Shells
